{"imp":{"icon":"https://script.bloodontheclocktower.com/images/icon/1 - Trouble Brewing/demon/Imp_icon.png","name":"Imp","type":"demon","ability":"Each night*, choose a player: they die. If you kill yourself this way, a Minion becomes the Imp."},"baron":{"icon":"https://script.bloodontheclocktower.com/images/icon/1 - Trouble Brewing/minion/Baron_icon.png","name":"Baron","type":"minion","ability":"There are extra Outsiders in play. [+2 Outsiders]"},"poisoner":{"icon":"https://script.bloodontheclocktower.com/images/icon/1 - Trouble Brewing/minion/Poisoner_icon.png","name":"Poisoner","type":"minion","ability":"Each night, choose a player: they are poisoned tonight and tomorrow day."},"scarletwoman":{"icon":"https://script.bloodontheclocktower.com/images/icon/1 - Trouble Brewing/minion/Scarlet Woman_icon.png","name":"Scarlet Woman","type":"minion","ability":"If there are 5 or more players alive & the Demon dies, you become the Demon. (Travellers don’t count)"},"spy":{"icon":"https://script.bloodontheclocktower.com/images/icon/1 - Trouble Brewing/minion/Spy_icon.png","name":"Spy","type":"minion","ability":"Each night, you see the Grimoire. You might register as good & as a Townsfolk or Outsider, even if dead."},"butler":{"icon":"https://script.bloodontheclocktower.com/images/icon/1 - Trouble Brewing/outsider/Butler_icon.png","name":"Butler","type":"outsider","ability":"Each night, choose a player (not yourself): tomorrow, you may only vote if they are voting too."},"drunk":{"icon":"https://script.bloodontheclocktower.com/images/icon/1 - Trouble Brewing/outsider/Drunk_icon.png","name":"Drunk","type":"outsider","ability":"You do not know you are the Drunk. You think you are a Townsfolk character, but you are not."},"recluse":{"icon":"https://script.bloodontheclocktower.com/images/icon/1 - Trouble Brewing/outsider/Recluse_icon.png","name":"Recluse","type":"outsider","ability":"You might register as evil & as a Minion or Demon, even if dead."},"saint":{"icon":"https://script.bloodontheclocktower.com/images/icon/1 - Trouble Brewing/outsider/Saint_icon.png","name":"Saint","type":"outsider","ability":"If you die by execution, your team loses."},"chef":{"icon":"https://script.bloodontheclocktower.com/images/icon/1 - Trouble Brewing/townsfolk/Chef_icon.png","name":"Chef","type":"townsfolk","ability":"You start knowing how many pairs of evil players there are."},"empath":{"icon":"https://script.bloodontheclocktower.com/images/icon/1 - Trouble Brewing/townsfolk/Empath_icon.png","name":"Empath","type":"townsfolk","ability":"Each night, you learn how many of your 2 alive neighbours are evil."},"fortuneteller":{"icon":"https://script.bloodontheclocktower.com/images/icon/1 - Trouble Brewing/townsfolk/Fortune Teller_icon.png","name":"Fortune Teller","type":"townsfolk","ability":"Each night, choose 2 players: you learn if either is a Demon. There is a good player that registers as a Demon to you."},"investigator":{"icon":"https://script.bloodontheclocktower.com/images/icon/1 - Trouble Brewing/townsfolk/Investigator_icon.png","name":"Investigator","type":"townsfolk","ability":"You start knowing that 1 of 2 players is a particular Minion."},"librarian":{"icon":"https://script.bloodontheclocktower.com/images/icon/1 - Trouble Brewing/townsfolk/Librarian_icon.png","name":"Librarian","type":"townsfolk","ability":"You start knowing that 1 of 2 players is a particular Outsider. (Or that zero are in play.)"},"mayor":{"icon":"https://script.bloodontheclocktower.com/images/icon/1 - Trouble Brewing/townsfolk/Mayor_icon.png","name":"Mayor","type":"townsfolk","ability":"If only 3 players live & no execution occurs, your team wins. If you die at night, another player might die instead."},"monk":{"icon":"https://script.bloodontheclocktower.com/images/icon/1 - Trouble Brewing/townsfolk/Monk_icon.png","name":"Monk","type":"townsfolk","ability":"Each night*, choose a player (not yourself): they are safe from the Demon tonight."},"ravenkeeper":{"icon":"https://script.bloodontheclocktower.com/images/icon/1 - Trouble Brewing/townsfolk/Ravenkeeper_icon.png","name":"Ravenkeeper","type":"townsfolk","ability":"If you die at night, you are woken to choose a player: you learn their character."},"slayer":{"icon":"https://script.bloodontheclocktower.com/images/icon/1 - Trouble Brewing/townsfolk/Slayer_icon.png","name":"Slayer","type":"townsfolk","ability":"Once per game, during the day, publicly choose a player: if they are the Demon, they die."},"soldier":{"icon":"https://script.bloodontheclocktower.com/images/icon/1 - Trouble Brewing/townsfolk/Soldier_icon.png","name":"Soldier","type":"townsfolk","ability":"You are safe from the Demon."},"undertaker":{"icon":"https://script.bloodontheclocktower.com/images/icon/1 - Trouble Brewing/townsfolk/Undertaker_icon.png","name":"Undertaker","type":"townsfolk","ability":"Each night*, you learn which character died by execution today."},"virgin":{"icon":"https://script.bloodontheclocktower.com/images/icon/1 - Trouble Brewing/townsfolk/Virgin_icon.png","name":"Virgin","type":"townsfolk","ability":"The 1st time you are nominated, if the nominator is a Townsfolk, they are executed immediately."},"washerwoman":{"icon":"https://script.bloodontheclocktower.com/images/icon/1 - Trouble Brewing/townsfolk/Washerwoman_icon.png","name":"Washerwoman","type":"townsfolk","ability":"You start knowing that 1 of 2 players is a particular Townsfolk."},"po":{"icon":"https://script.bloodontheclocktower.com/images/icon/2 - Bad Moon Rising/demon/Po_icon.png","name":"Po","type":"demon","ability":"Each night*, you may choose a player: they die. If your last choice was no-one, choose 3 players tonight."},"pukka":{"icon":"https://script.bloodontheclocktower.com/images/icon/2 - Bad Moon Rising/demon/Pukka_icon.png","name":"Pukka","type":"demon","ability":"Each night, choose a player: they are poisoned. The previously poisoned player dies then becomes healthy."},"shabaloth":{"icon":"https://script.bloodontheclocktower.com/images/icon/2 - Bad Moon Rising/demon/Shabaloth_icon.png","name":"Shabaloth","type":"demon","ability":"Each night*, choose 2 players: they die. A dead player you chose last night might be regurgitated."},"zombuul":{"icon":"https://script.bloodontheclocktower.com/images/icon/2 - Bad Moon Rising/demon/Zombuul_icon.png","name":"Zombuul","type":"demon","ability":"Each night*, if no-one died today, choose a player: they die. The 1st time you die, you live but register as dead."},"assassin":{"icon":"https://script.bloodontheclocktower.com/images/icon/2 - Bad Moon Rising/minion/Assassin_icon.png","name":"Assassin","type":"minion","ability":"Once per game, at night*, choose a player: they die, even if for some reason they could not."},"devil'sadvocate":{"icon":"https://script.bloodontheclocktower.com/images/icon/2 - Bad Moon Rising/minion/Devil's Advocate_icon.png"},"godfather":{"icon":"https://script.bloodontheclocktower.com/images/icon/2 - Bad Moon Rising/minion/Godfather_icon.png","name":"Godfather","type":"minion","ability":"You start knowing which Outsiders are in play. If 1 died today, choose a player tonight: they die. [−1 or +1 Outsider]"},"mastermind":{"icon":"https://script.bloodontheclocktower.com/images/icon/2 - Bad Moon Rising/minion/Mastermind_icon.png","name":"Mastermind","type":"minion","ability":"If the Demon dies by execution (ending the game), play for 1 more day. If a player is then executed, their team loses."},"goon":{"icon":"https://script.bloodontheclocktower.com/images/icon/2 - Bad Moon Rising/outsider/Goon_icon.png","name":"Goon","type":"outsider","ability":"Each night, the 1st player to choose you with their ability is drunk until dusk. You become their alignment."},"lunatic":{"icon":"https://script.bloodontheclocktower.com/images/icon/2 - Bad Moon Rising/outsider/Lunatic_icon.png","name":"Lunatic","type":"outsider","ability":"You think you are a Demon, but you are not. The Demon knows who you are & who you choose at night."},"moonchild":{"icon":"https://script.bloodontheclocktower.com/images/icon/2 - Bad Moon Rising/outsider/Moonchild_icon.png","name":"Moonchild","type":"outsider","ability":"When you learn that you died, publicly choose 1 alive player. Tonight, if it was a good player, they die."},"tinker":{"icon":"https://script.bloodontheclocktower.com/images/icon/2 - Bad Moon Rising/outsider/Tinker_icon.png","name":"Tinker","type":"outsider","ability":"You might die at any time."},"chambermaid":{"icon":"https://script.bloodontheclocktower.com/images/icon/2 - Bad Moon Rising/townsfolk/Chambermaid_icon.png","name":"Chambermaid","type":"townsfolk","ability":"Each night, choose 2 alive players (not yourself): you learn how many woke tonight due to their ability."},"courtier":{"icon":"https://script.bloodontheclocktower.com/images/icon/2 - Bad Moon Rising/townsfolk/Courtier_icon.png","name":"Courtier","type":"townsfolk","ability":"Once per game, at night, choose a character: they are drunk for 3 nights & 3 days."},"exorcist":{"icon":"https://script.bloodontheclocktower.com/images/icon/2 - Bad Moon Rising/townsfolk/Exorcist_icon.png","name":"Exorcist","type":"townsfolk","ability":"Each night*, choose a player (different to last night): the Demon, if chosen, learns who you are then doesn't wake tonight."},"fool":{"icon":"https://script.bloodontheclocktower.com/images/icon/2 - Bad Moon Rising/townsfolk/Fool_icon.png","name":"Fool","type":"townsfolk","ability":"The first time you die, you don't."},"gambler":{"icon":"https://script.bloodontheclocktower.com/images/icon/2 - Bad Moon Rising/townsfolk/Gambler_icon.png","name":"Gambler","type":"townsfolk","ability":"Each night*, choose a player & guess their character: if you guess wrong, you die."},"gossip":{"icon":"https://script.bloodontheclocktower.com/images/icon/2 - Bad Moon Rising/townsfolk/Gossip_icon.png","name":"Gossip","type":"townsfolk","ability":"Each day, you may make a public statement. Tonight, if it was true, a player dies."},"grandmother":{"icon":"https://script.bloodontheclocktower.com/images/icon/2 - Bad Moon Rising/townsfolk/Grandmother_icon.png","name":"Grandmother","type":"townsfolk","ability":"You start knowing a good player & their character. If the Demon kills them, you die too."},"innkeeper":{"icon":"https://script.bloodontheclocktower.com/images/icon/2 - Bad Moon Rising/townsfolk/Innkeeper_icon.png","name":"Innkeeper","type":"townsfolk","ability":"Each night*, choose 2 players: they can't die tonight, but 1 is drunk until dusk."},"minstrel":{"icon":"https://script.bloodontheclocktower.com/images/icon/2 - Bad Moon Rising/townsfolk/Minstrel_icon.png","name":"Minstrel","type":"townsfolk","ability":"When a Minion dies by execution, all other players (except Travellers) are drunk until dusk tomorrow."},"pacifist":{"icon":"https://script.bloodontheclocktower.com/images/icon/2 - Bad Moon Rising/townsfolk/Pacifist_icon.png","name":"Pacifist","type":"townsfolk","ability":"Executed good players might not die."},"professor":{"icon":"https://script.bloodontheclocktower.com/images/icon/2 - Bad Moon Rising/townsfolk/Professor_icon.png","name":"Professor","type":"townsfolk","ability":"Once per game, at night*, choose a dead player: if they are a Townsfolk, they are resurrected."},"sailor":{"icon":"https://script.bloodontheclocktower.com/images/icon/2 - Bad Moon Rising/townsfolk/Sailor_icon.png","name":"Sailor","type":"townsfolk","ability":"Each night, choose an alive player: either you or they are drunk until dusk. You can't die."},"tealady":{"icon":"https://script.bloodontheclocktower.com/images/icon/2 - Bad Moon Rising/townsfolk/Tea Lady_icon.png","name":"Tea Lady","type":"townsfolk","ability":"If both your alive neighbours are good, they can't die."},"fanggu":{"icon":"https://script.bloodontheclocktower.com/images/icon/3 - Sects and Violets/demon/Fang Gu_icon.png","name":"Fang Gu","type":"demon","ability":"Each night*, choose a player: they die. The 1st Outsider this kills becomes an evil Fang Gu & you die instead. [+1 Outsider]"},"nodashii":{"icon":"https://script.bloodontheclocktower.com/images/icon/3 - Sects and Violets/demon/No Dashii_icon.png","name":"No Dashii","type":"demon","ability":"Each night*, choose a player: they die. Your 2 Townsfolk neighbours are poisoned."},"vigormortis":{"icon":"https://script.bloodontheclocktower.com/images/icon/3 - Sects and Violets/demon/Vigormortis_icon.png","name":"Vigormortis","type":"demon","ability":"Each night*, choose a player: they die. Minions you kill keep their ability & poison 1 Townsfolk neighbour. [−1 Outsider]"},"vortox":{"icon":"https://script.bloodontheclocktower.com/images/icon/3 - Sects and Violets/demon/Vortox_icon.png","name":"Vortox","type":"demon","ability":"Each night*, choose a player: they die. Townsfolk abilities yield false info. Each day, if no-one is executed, evil wins."},"cerenovus":{"icon":"https://script.bloodontheclocktower.com/images/icon/3 - Sects and Violets/minion/Cerenovus_icon.png","name":"Cerenovus","type":"minion","ability":"Each night, choose a player & a good character: they are “mad” they are this character tomorrow, or might be executed."},"eviltwin":{"icon":"https://script.bloodontheclocktower.com/images/icon/3 - Sects and Violets/minion/Evil Twin_icon.png","name":"Evil Twin","type":"minion","ability":"You & an opposing player know each other. If the good player is executed, evil wins. Good can't win if you both live."},"pithag":{"icon":"https://script.bloodontheclocktower.com/images/icon/3 - Sects and Violets/minion/Pit-Hag_icon.png","name":"Pit-Hag","type":"minion","ability":"Each night*, choose a player & a character they become (if not-in-play). If a Demon is made, deaths tonight are arbitrary."},"witch":{"icon":"https://script.bloodontheclocktower.com/images/icon/3 - Sects and Violets/minion/Witch_icon.png","name":"Witch","type":"minion","ability":"Each night, choose a player: if they nominate tomorrow, they die. If just 3 players live, you lose this ability."},"barber":{"icon":"https://script.bloodontheclocktower.com/images/icon/3 - Sects and Violets/outsider/Barber_icon.png","name":"Barber","type":"outsider","ability":"If you died today or tonight, the Demon may choose 2 players (not another Demon) to swap characters."},"klutz":{"icon":"https://script.bloodontheclocktower.com/images/icon/3 - Sects and Violets/outsider/Klutz_icon.png","name":"Klutz","type":"outsider","ability":"When you learn that you died, publicly choose 1 alive player: if they are evil, your team loses."},"mutant":{"icon":"https://script.bloodontheclocktower.com/images/icon/3 - Sects and Violets/outsider/Mutant_icon.png","name":"Mutant","type":"outsider","ability":"If you are “mad” about being an Outsider, you might be executed."},"sweetheart":{"icon":"https://script.bloodontheclocktower.com/images/icon/3 - Sects and Violets/outsider/Sweetheart_icon.png","name":"Sweetheart","type":"outsider","ability":"When you die, 1 player is drunk from now on."},"artist":{"icon":"https://script.bloodontheclocktower.com/images/icon/3 - Sects and Violets/townsfolk/Artist_icon.png","name":"Artist","type":"townsfolk","ability":"Once per game, during the day, privately ask the Storyteller any yes/no question."},"clockmaker":{"icon":"https://script.bloodontheclocktower.com/images/icon/3 - Sects and Violets/townsfolk/Clockmaker_icon.png","name":"Clockmaker","type":"townsfolk","ability":"You start knowing how many steps from the Demon to its nearest Minion."},"dreamer":{"icon":"https://script.bloodontheclocktower.com/images/icon/3 - Sects and Violets/townsfolk/Dreamer_icon.png","name":"Dreamer","type":"townsfolk","ability":"Each night, choose a player (not yourself or Travellers): you learn 1 good and 1 evil character, 1 of which is correct."},"flowergirl":{"icon":"https://script.bloodontheclocktower.com/images/icon/3 - Sects and Violets/townsfolk/Flowergirl_icon.png","name":"Flowergirl","type":"townsfolk","ability":"Each night*, you learn if a Demon voted today."},"juggler":{"icon":"https://script.bloodontheclocktower.com/images/icon/3 - Sects and Violets/townsfolk/Juggler_icon.png","name":"Juggler","type":"townsfolk","ability":"On your 1st day, publicly guess up to 5 players' characters. That night, you learn how many you got correct."},"mathematician":{"icon":"https://script.bloodontheclocktower.com/images/icon/3 - Sects and Violets/townsfolk/Mathematician_icon.png","name":"Mathematician","type":"townsfolk","ability":"Each night, you learn how many players’ abilities worked abnormally (since dawn) due to another character's ability."},"oracle":{"icon":"https://script.bloodontheclocktower.com/images/icon/3 - Sects and Violets/townsfolk/Oracle_icon.png","name":"Oracle","type":"townsfolk","ability":"Each night*, you learn how many dead players are evil."},"philosopher":{"icon":"https://script.bloodontheclocktower.com/images/icon/3 - Sects and Violets/townsfolk/Philosopher_icon.png","name":"Philosopher","type":"townsfolk","ability":"Once per game, at night, choose a good character: gain that ability. If this character is in play, they are drunk."},"sage":{"icon":"https://script.bloodontheclocktower.com/images/icon/3 - Sects and Violets/townsfolk/Sage_icon.png","name":"Sage","type":"townsfolk","ability":"If the Demon kills you, you learn that it is 1 of 2 players."},"savant":{"icon":"https://script.bloodontheclocktower.com/images/icon/3 - Sects and Violets/townsfolk/Savant_icon.png","name":"Savant","type":"townsfolk","ability":"Each day, you may visit the Storyteller to learn 2 things in private: 1 is true & 1 is false."},"seamstress":{"icon":"https://script.bloodontheclocktower.com/images/icon/3 - Sects and Violets/townsfolk/Seamstress_icon.png","name":"Seamstress","type":"townsfolk","ability":"Once per game, at night, choose 2 players (not yourself): you learn if they are the same alignment."},"snakecharmer":{"icon":"https://script.bloodontheclocktower.com/images/icon/3 - Sects and Violets/townsfolk/Snake Charmer_icon.png","name":"Snake Charmer","type":"townsfolk","ability":"Each night, choose an alive player: a chosen Demon swaps characters & alignments with you & is then poisoned."},"towncrier":{"icon":"https://script.bloodontheclocktower.com/images/icon/3 - Sects and Violets/townsfolk/Town Crier_icon.png","name":"Town Crier","type":"townsfolk","ability":"Each night*, you learn if a Minion nominated today."},"riot":{"icon":"https://script.bloodontheclocktower.com/images/icon/4 - Experimental/demon/Riot_icon.png","name":"Riot","type":"demon","ability":"Nominees die, but may nominate again immediately (on day 3, they must). After day 3, evil wins. [All Minions are Riot]"},"alhadikhia":{"icon":"https://script.bloodontheclocktower.com/images/icon/4 - Experimental/demon/Al-Hadikhia_icon.png?t=456","name":"Al-Hadikhia","type":"demon","ability":"Each night*, choose 3 players (all players learn who): each silently chooses to live or die, but if all live, all die."},"legion":{"icon":"https://script.bloodontheclocktower.com/images/icon/4 - Experimental/demon/Legion_icon.png?t=456","name":"Legion","type":"demon","ability":"Each night*, a player might die. Executions fail if only evil voted. You register as a Minion too. [Most players are Legion]"},"leviathan":{"icon":"https://script.bloodontheclocktower.com/images/icon/4 - Experimental/demon/Leviathan_icon.png?t=456","name":"Leviathan","type":"demon","ability":"If more than 1 good player is executed, you win. All players know you are in play. After day 5, evil wins."},"lleech":{"icon":"https://script.bloodontheclocktower.com/images/icon/4 - Experimental/demon/Lleech_icon.png","name":"Lleech","type":"demon","ability":"Each night*, choose a player: they die. You start by choosing an alive player: they are poisoned - you die if & only if they die."},"lil'monsta":{"icon":"https://script.bloodontheclocktower.com/images/icon/4 - Experimental/demon/Lil' Monsta_icon.png?t=456"},"boomdandy":{"icon":"https://script.bloodontheclocktower.com/images/icon/4 - Experimental/minion/Boomdandy_icon.png","name":"Boomdandy","type":"minion","ability":"If you are executed, all but 3 players die. 1 minute later, the player with the most players pointing at them dies."},"goblin":{"icon":"https://script.bloodontheclocktower.com/images/icon/4 - Experimental/minion/Goblin_icon.png?t=456","name":"Goblin","type":"minion","ability":"If you publicly claim to be the Goblin when nominated & are executed that day, your team wins."},"fearmonger":{"icon":"https://script.bloodontheclocktower.com/images/icon/4 - Experimental/minion/Fearmonger_icon.png?t=456","name":"Fearmonger","type":"minion","ability":"Each night, choose a player. If you nominate & execute them, their team loses. All players know if you choose a new player."},"widow":{"icon":"https://script.bloodontheclocktower.com/images/icon/4 - Experimental/minion/Widow_icon.png?t=456","name":"Widow","type":"minion","ability":"On your 1st night, look at the Grimoire and choose a player: they are poisoned. 1 good player knows a Widow is in play."},"marionette":{"icon":"https://script.bloodontheclocktower.com/images/icon/4 - Experimental/minion/Marionette_icon.png?t=456","name":"Marionette","type":"minion","ability":"You think you are a good character but you are not. The Demon knows who you are. [You neighbour the Demon]"},"mezepheles":{"icon":"https://script.bloodontheclocktower.com/images/icon/4 - Experimental/minion/Mezepheles_icon.png?t=456","name":"Mezepheles","type":"minion","ability":"You start knowing a secret word. The 1st good player to say this word becomes evil that night."},"psychopath":{"icon":"https://script.bloodontheclocktower.com/images/icon/4 - Experimental/minion/Psychopath_icon.png?t=456","name":"Psychopath","type":"minion","ability":"Each day, before nominations, you may publicly choose a player: they die. If executed, you only die if you lose roshambo."},"acrobat":{"icon":"https://script.bloodontheclocktower.com/images/icon/4 - Experimental/outsider/Acrobat_icon.png?t=456","name":"Acrobat","type":"outsider","ability":"Each night*, if either good living neighbour is drunk or poisoned, you die."},"damsel":{"icon":"https://script.bloodontheclocktower.com/images/icon/4 - Experimental/outsider/Damsel_icon.png?t=456","name":"Damsel","type":"outsider","ability":"All Minions know you are in play. If a Minion publicly guesses you (once), your team loses."},"golem":{"icon":"https://script.bloodontheclocktower.com/images/icon/4 - Experimental/outsider/Golem_icon.png","name":"Golem","type":"outsider","ability":"You may only nominate once per game. When you do, if the nominee is not the Demon, they die."},"heretic":{"icon":"https://script.bloodontheclocktower.com/images/icon/4 - Experimental/outsider/Heretic_icon.png?t=456","name":"Heretic","type":"outsider","ability":"Whoever wins, loses & whoever loses, wins, even if you are dead."},"politician":{"icon":"https://script.bloodontheclocktower.com/images/icon/4 - Experimental/outsider/Politician_icon.png?t=456","name":"Politician","type":"outsider","ability":"If you were the player most responsible for your team losing, you change alignment & win, even if dead."},"puzzlemaster":{"icon":"https://script.bloodontheclocktower.com/images/icon/4 - Experimental/outsider/Puzzlemaster_icon.png","name":"Puzzlemaster","type":"outsider","ability":"1 player is drunk, even if you die. If you guess (once) who it is, learn the Demon player, but guess wrong & get false info."},"snitch":{"icon":"https://script.bloodontheclocktower.com/images/icon/4 - Experimental/outsider/Snitch_icon.png","name":"Snitch","type":"outsider","ability":"Minions start knowing 3 not-in-play characters."},"amnesiac":{"icon":"https://script.bloodontheclocktower.com/images/icon/4 - Experimental/townsfolk/Amnesiac_icon.png?t=456","name":"Amnesiac","type":"townsfolk","ability":"You do not know what your ability is. Each day, privately guess what it is: you learn how accurate you are."},"atheist":{"icon":"https://script.bloodontheclocktower.com/images/icon/4 - Experimental/townsfolk/Atheist_icon.png","name":"Atheist","type":"townsfolk","ability":"The Storyteller can break the game rules & if executed, good wins, even if you are dead. [No evil characters]"},"balloonist":{"icon":"https://script.bloodontheclocktower.com/images/icon/4 - Experimental/townsfolk/Balloonist_icon.png?t=456","name":"Balloonist","type":"townsfolk","ability":"Each night, you learn 1 player of each character type, until there are no more types to learn. [+1 Outsider]"},"bountyhunter":{"icon":"https://script.bloodontheclocktower.com/images/icon/4 - Experimental/townsfolk/Bounty Hunter_icon.png?t=456","name":"Bounty Hunter","type":"townsfolk","ability":"You start knowing 1 evil player. If the player you know dies, you learn another evil player tonight. [1 Townsfolk is evil]"},"cannibal":{"icon":"https://script.bloodontheclocktower.com/images/icon/4 - Experimental/townsfolk/Cannibal_icon.png?t=456","name":"Cannibal","type":"townsfolk","ability":"You have the ability of the recently killed executee. If they are evil, you are poisoned until a good player dies by execution."},"cultleader":{"icon":"https://script.bloodontheclocktower.com/images/icon/4 - Experimental/townsfolk/Cult Leader_icon.png?t=456","name":"Cult Leader","type":"townsfolk","ability":"Each night, you become the alignment of an alive neighbour. If all good players choose to join your cult, your team wins."},"farmer":{"icon":"https://script.bloodontheclocktower.com/images/icon/4 - Experimental/townsfolk/Farmer_icon.png","name":"Farmer","type":"townsfolk","ability":"If you die at night, an alive good player becomes a Farmer."},"fisherman":{"icon":"https://script.bloodontheclocktower.com/images/icon/4 - Experimental/townsfolk/Fisherman_icon.png?t=456","name":"Fisherman","type":"townsfolk","ability":"Once per game, during the day, visit the Storyteller for some advice to help you win."},"general":{"icon":"https://script.bloodontheclocktower.com/images/icon/4 - Experimental/townsfolk/General_icon.png?t=456","name":"General","type":"townsfolk","ability":"Each night, you learn which alignment the Storyteller believes is winning: good, evil, or neither."},"lycanthrope":{"icon":"https://script.bloodontheclocktower.com/images/icon/4 - Experimental/townsfolk/Lycanthrope_icon.png?t=456","name":"Lycanthrope","type":"townsfolk","ability":"Each night*, choose a living player: if good, they die, but they are the only player that can die tonight."},"huntsman":{"icon":"https://script.bloodontheclocktower.com/images/icon/4 - Experimental/townsfolk/Huntsman_icon.png?t=456","name":"Huntsman","type":"townsfolk","ability":"Once per game, at night, choose a living player: the Damsel, if chosen, becomes a not-in-play Townsfolk. [+the Damsel]"},"magician":{"icon":"https://script.bloodontheclocktower.com/images/icon/4 - Experimental/townsfolk/Magician_icon.png","name":"Magician","type":"townsfolk","ability":"The Demon thinks you are a Minion. Minions think you are a Demon."},"noble":{"icon":"https://script.bloodontheclocktower.com/images/icon/4 - Experimental/townsfolk/Noble_icon.png?t=123","name":"Noble","type":"townsfolk","ability":"You start knowing 3 players, 1 and only 1 of which is evil."},"pixie":{"icon":"https://script.bloodontheclocktower.com/images/icon/4 - Experimental/townsfolk/Pixie_icon.png?t=456","name":"Pixie","type":"townsfolk","ability":"You start knowing 1 in-play Townsfolk. If you were mad that you were this character, you gain their ability when they die."},"preacher":{"icon":"https://script.bloodontheclocktower.com/images/icon/4 - Experimental/townsfolk/Preacher_icon.png?t=456","name":"Preacher","type":"townsfolk","ability":"Each night, choose a player: a Minion, if chosen, learns this. All chosen Minions have no ability."},"poppygrower":{"icon":"https://script.bloodontheclocktower.com/images/icon/4 - Experimental/townsfolk/Poppy Grower_icon.png?t=456","name":"Poppy Grower","type":"townsfolk","ability":"Minions & Demons do not know each other. If you die, they learn who each other are that night."},"king":{"icon":"https://script.bloodontheclocktower.com/images/icon/4 - Experimental/townsfolk/King_icon.png?t=123","name":"King","type":"townsfolk","ability":"Each night, if the dead outnumber the living, you learn 1 alive character. The Demon knows who you are."},"choirboy":{"icon":"https://script.bloodontheclocktower.com/images/icon/4 - Experimental/townsfolk/Choirboy_icon.png?t=123","name":"Choirboy","type":"townsfolk","ability":"If the Demon kills the King, you learn which player is the Demon. [+ the King]"},"engineer":{"icon":"https://script.bloodontheclocktower.com/images/icon/4 - Experimental/townsfolk/Engineer_icon.png?t=123","name":"Engineer","type":"townsfolk","ability":"Once per game, at night, choose which Minions or which Demon is in play."},"alchemist":{"icon":"https://script.bloodontheclocktower.com/images/icon/4 - Experimental/townsfolk/Alchemist_icon.png","name":"Alchemist","type":"townsfolk","ability":"You have a not-in-play Minion ability."},"nightwatchman":{"icon":"https://script.bloodontheclocktower.com/images/icon/4 - Experimental/townsfolk/Nightwatchman_icon.png","name":"Nightwatchman","type":"townsfolk","ability":"Once per game, at night, choose a player: they learn who you are."},"organgrinder":{"icon":"https://script.bloodontheclocktower.com/images/icon/4 - Experimental/minion/Organ Grinder_icon.png","name":"Organ Grinder","type":"minion","ability":"All players keep their eyes closed when voting & the vote tally is secret. Votes for you only count if you vote."},"vizier":{"icon":"https://script.bloodontheclocktower.com/images/icon/4 - Experimental/minion/Vizier_icon.png","name":"Vizier","type":"minion","ability":"All players know who you are. You can not die during the day. If good voted, you may choose to execute immediately."},"knight":{"icon":"https://script.bloodontheclocktower.com/images/icon/4 - Experimental/townsfolk/Knight_icon.png","name":"Knight","type":"townsfolk","ability":"You start knowing 2 players that are not the Demon."},"steward":{"icon":"https://script.bloodontheclocktower.com/images/icon/4 - Experimental/townsfolk/Steward_icon.png","name":"Steward","type":"townsfolk","ability":"You start knowing 1 good player."},"angel":{"icon":"https://script.bloodontheclocktower.com/images/icon/Extras/fabled/Angel_icon.png","name":"Angel","type":"fabled","ability":"Something bad might happen to whoever is most responsible for the death of a new player."},"buddhist":{"icon":"https://script.bloodontheclocktower.com/images/icon/Extras/fabled/Buddhist_icon.png","name":"Buddhist","type":"fabled","ability":"For the first 2 minutes of each day, veteran players may not talk."},"djinn":{"icon":"https://script.bloodontheclocktower.com/images/icon/Extras/fabled/Djinn_icon.png","name":"Djinn","type":"fabled","ability":"Use the Djinn's special rule. All players know what it is."},"doomsayer":{"icon":"https://script.bloodontheclocktower.com/images/icon/Extras/fabled/Doomsayer_icon.png","name":"Doomsayer","type":"fabled","ability":"If 4 or more players live, each living player may publicly choose (once per game) that a player of their own alignment dies."},"duchess":{"icon":"https://script.bloodontheclocktower.com/images/icon/Extras/fabled/Duchess_icon.png","name":"Duchess","type":"fabled","ability":"Each day, 3 players may choose to visit you. At night*, each visitor learns how many visitors are evil, but 1 gets false info."},"fibbin":{"icon":"https://script.bloodontheclocktower.com/images/icon/Extras/fabled/Fibbin_icon.png","name":"Fibbin","type":"fabled","ability":"Once per game, 1 good player might get false information."},"fiddler":{"icon":"https://script.bloodontheclocktower.com/images/icon/Extras/fabled/Fiddler_icon.png","name":"Fiddler","type":"fabled","ability":"Once per game, the Demon secretly chooses an opposing player: all players choose which of these 2 players win."},"hell'slibrarian":{"icon":"https://script.bloodontheclocktower.com/images/icon/Extras/fabled/Hell's Librarian_icon.png"},"revolutionary":{"icon":"https://script.bloodontheclocktower.com/images/icon/Extras/fabled/Revolutionary_icon.png","name":"Revolutionary","type":"fabled","ability":"2 neighboring players are known to be the same alignment. Once per game, one of them registers falsely."},"sentinel":{"icon":"https://script.bloodontheclocktower.com/images/icon/Extras/fabled/Sentinel_icon.png","name":"Sentinel","type":"fabled","ability":"There might be 1 extra or 1 fewer Outsider in play."},"spiritofivory":{"icon":"https://script.bloodontheclocktower.com/images/icon/Extras/fabled/Spirit Of Ivory_icon.png","name":"Spirit of Ivory","type":"fabled","ability":"There can't be more than 1 extra evil player."},"stormcatcher":{"icon":"https://script.bloodontheclocktower.com/images/icon/Extras/fabled/Storm Catcher_icon.png?t=456","name":"Storm Catcher","type":"fabled","ability":"Name a good character. If in play, they can only die by execution, but evil players learn which player it is."},"toymaker":{"icon":"https://script.bloodontheclocktower.com/images/icon/Extras/fabled/Toymaker_icon.png","name":"Toymaker","type":"fabled","ability":"The Demon may choose not to attack & must do this at least once per game. Evil players get normal starting info."},"apprentice":{"icon":"https://script.bloodontheclocktower.com/images/icon/Extras/travellers/Apprentice_icon.png","name":"Apprentice","type":"traveler","ability":"On your 1st night, you gain a Townsfolk ability (if good), or a Minion ability (if evil)."},"barista":{"icon":"https://script.bloodontheclocktower.com/images/icon/Extras/travellers/Barista_icon.png","name":"Barista","type":"traveler","ability":"Each night, until dusk, 1) a player becomes sober, healthy and gets true info, or 2) their ability works twice. They learn which."},"beggar":{"icon":"https://script.bloodontheclocktower.com/images/icon/Extras/travellers/Beggar_icon.png","name":"Beggar","type":"traveler","ability":"You must use a vote token to vote. Dead players may choose to give you theirs. If so, you learn their alignment. You are sober & healthy."},"bishop":{"icon":"https://script.bloodontheclocktower.com/images/icon/Extras/travellers/Bishop_icon.png","name":"Bishop","type":"traveler","ability":"Only the Storyteller can nominate. At least 1 opposite player must be nominated each day."},"bonecollector":{"icon":"https://script.bloodontheclocktower.com/images/icon/Extras/travellers/Bone Collector_icon.png","name":"Bone Collector","type":"traveler","ability":"Once per game, at night, choose a dead player: they regain their ability until dusk."},"bureaucrat":{"icon":"https://script.bloodontheclocktower.com/images/icon/Extras/travellers/Bureaucrat_icon.png","name":"Bureaucrat","type":"traveler","ability":"Each night, choose a player (not yourself): their vote counts as 3 votes tomorrow."},"butcher":{"icon":"https://script.bloodontheclocktower.com/images/icon/Extras/travellers/Butcher_icon.png","name":"Butcher","type":"traveler","ability":"Each day, after the 1st execution, you may nominate again."},"deviant":{"icon":"https://script.bloodontheclocktower.com/images/icon/Extras/travellers/Deviant_icon.png","name":"Deviant","type":"traveler","ability":"If you were funny today, you cannot die by exile."},"gangster":{"icon":"https://script.bloodontheclocktower.com/images/icon/Extras/travellers/Gangster_icon.png","name":"Gangster","type":"traveler","ability":"Once per day, you may choose to kill an alive neighbour, if your other alive neighbour agrees."},"gunslinger":{"icon":"https://script.bloodontheclocktower.com/images/icon/Extras/travellers/Gunslinger_icon.png","name":"Gunslinger","type":"traveler","ability":"Each day, after the 1st vote has been tallied, you may choose a player that voted: they die."},"harlot":{"icon":"https://script.bloodontheclocktower.com/images/icon/Extras/travellers/Harlot_icon.png","name":"Harlot","type":"traveler","ability":"Each night*, choose a living player: if they agree, you learn their character, but you both might die."},"judge":{"icon":"https://script.bloodontheclocktower.com/images/icon/Extras/travellers/Judge_icon.png","name":"Judge","type":"traveler","ability":"Once per game, if another player nominated, you may choose to force the current execution to pass or fail."},"matron":{"icon":"https://script.bloodontheclocktower.com/images/icon/Extras/travellers/Matron_icon.png","name":"Matron","type":"traveler","ability":"Each day, you may choose up to 3 sets of 2 players to swap seats. Players may not leave their seats to talk in private."},"scapegoat":{"icon":"https://script.bloodontheclocktower.com/images/icon/Extras/travellers/Scapegoat_icon.png","name":"Scapegoat","type":"traveler","ability":"If a player of your alignment is executed, you might be executed instead."},"thief":{"icon":"https://script.bloodontheclocktower.com/images/icon/Extras/travellers/Thief_icon.png","name":"Thief","type":"traveler","ability":"Each night, choose a player (not yourself): their vote counts negatively tomorrow."},"voudon":{"icon":"https://script.bloodontheclocktower.com/images/icon/Extras/travellers/Voudon_icon.png","name":"Voudon","type":"traveler","ability":"Only you and the dead can vote. They don't need a vote token to do so. A 50% majority is not required."},"emissary":{"name":"Emissary","type":"townsfolk","ability":""},"genie":{"name":"Genie","type":"townsfolk","ability":""},"labrat":{"name":"Lab Rat","type":"townsfolk","ability":"Each night, choose 2 alive players (not yourself): learn if either is a source of active poisoning."},"trojanhorse":{"name":"Trojan Horse","type":"outsider","ability":""},"arburri":{"name":"Arburri","type":"minion","ability":""},"devilsadvocate":{"name":"Devil's Advocate","type":"minion","ability":"Each night, choose a living player (different to last night): if executed tomorrow, they don't die."},"mephit":{"name":"Mephit","type":"minion","ability":"You start knowing a secret word. The 1st good player to say this word becomes evil that night."},"lilmonsta":{"name":"Lil' Monsta","type":"demon","ability":"Each night, Minions choose who babysits Lil' Monsta's token & \"is the Demon\". A player dies each night*. [+1 Minion]"},"malopcion":{"name":"Mal-Opción","type":"demon","ability":""},"hellslibrarian":{"name":"Hell's Librarian","type":"fabled","ability":"Something bad might happen to whoever talks when the Storyteller has asked for silence."}}